pylibosrm/__init__.py
pylibosrm/osrm_wrapper.cpython-37m-x86_64-linux-gnu.so
pylibosrm-0.1.1.dist-info/LICENSE
pylibosrm-0.1.1.dist-info/METADATA
pylibosrm-0.1.1.dist-info/WHEEL
pylibosrm-0.1.1.dist-info/top_level.txt
pylibosrm-0.1.1.dist-info/RECORD
